fasthelp.py
gpuinfo.py
fasthelp-1.1.3.dist-info/License.md
fasthelp-1.1.3.dist-info/METADATA
fasthelp-1.1.3.dist-info/WHEEL
fasthelp-1.1.3.dist-info/top_level.txt
fasthelp-1.1.3.dist-info/RECORD
