Metadata-Version: 2.1
Name: fasthelp
Version: 1.1.3
Summary: An Useful Python Helper that Bundles some functions (And added some new ones!)
Home-page: https://www.github.com/Unknownuserfrommars/fasthelp
Author: Ziyan Zhou
Author-email: unknownuserfrommars@protonmail.com
Maintainer: Unknownuserfrommars
Maintainer-email: unknownuserfrommars@protonmail.com
License: MIT
Classifier: Programming Language :: Python :: 3
Classifier: License :: OSI Approved :: MIT License
Classifier: Operating System :: OS Independent
Requires-Python: >=3.10
License-File: License.md
Requires-Dist: numpy >=1.26
Requires-Dist: pandas >=2.2
Requires-Dist: openai >=1.51
Requires-Dist: python-docx >=1.1.0
Requires-Dist: python-pptx >=1.0.0
Requires-Dist: distro >=1.9.0
Requires-Dist: psutil >=6.0.0
